Workbook

Sheet Resort_Rates
A1: Rooms Rates | I1: Services Rates
A2: Room_ID | B2: Cateogry | C2: Room_Type | D2: Capacity | E2: Summe_Rates (Peak) | F2: Winter_Rates (Off_Peak) | G2: Operating_Cost | I2: Room_Service | J2: 50 | K2: Charged once per stay
A3: R_101 | B3: Standard | C3: Garden Studio | D3: 1 | E3: 300 | F3: 250 | G3: 260 | I3: Laundry_Service | J3: 30 | K3: Charged once per stay
A4: R_102 | B4: Standard | C4: Solo Cabana | D4: 1 | E4: 300 | F4: 250 | G4: 260 | I4: Spa_Service | J4: 250 | K4: Per session
A5: R_103 | B5: Standard | C5: Double Studio | D5: 2 | E5: 450 | F5: 350 | G5: 370 | I5: Late Checkout | J5: 100 | K5: Per stay
A6: R_104 | B6: Standard | C6: Twin Balcony | D6: 2 | E6: 450 | F6: 350 | G6: 400
A7: R_105 | B7: Deluxe | C7: Garden View | D7: 2 | E7: 550 | F7: 450 | G7: 450
A8: R_106 | B8: Deluxe | C8: Poolside Retreat | D8: 2 | E8: 550 | F8: 450 | G8: 450 | I8: Packages
A9: R_107 | B9: Deluxe | C9: Ocean View | D9: 3 | E9: 700 | F9: 600 | G9: 600 | I9: Package_ID | J9: Package_Name | K9: Duration | L9: Flat_Rate | M9: Discount
A10: R_108 | B10: Deluxe | C10: Family Triple | D10: 3 | E10: 700 | F10: 600 | G10: 650 | I10: PKG_01 | J10: Presidential Ocean pkg | K10: 6 Nights | L10: 2199 | M10: 20% off
A11: R_109 | B11: Executive | C11: Junior Suite | D11: 2 | E11: 850 | F11: 750 | G11: 690 | I11: PKG_02 | J11: Family fum Bundle | K11: 4 Nights | L11: 2499 | M11: 10% off
A12: R_110 | B12: Executive | C12: Presidential | D12: 4 | E12: 1200 | F12: 1100 | G12: 800 | I12: PKG_03 | J12: Executive Beach Pkg | K12: 3 Nights | L12: 1299 | M12: 15% off
A13: R_111 | B13: Executive | C13: Grand Villa | D13: 6 | E13: 1800 | F13: 1700 | G13: 1150 | I13: PKG_04 | J13: Romantic Deluxe Pkg | K13: 2 Nights | L13: 999 | M13: 25% off
A14: R_112 | B14: Executive | C14: Royal Penthouse | D14: 4 | E14: 1200 | F14: 1100 | G14: 1090
A15: R_113 | B15: Standard | C15: Cozy Studio | D15: 1 | E15: 300 | F15: 250 | G15: 120
A16: R_114 | B16: Standard | C16: Garden Terrace | D16: 2 | E16: 450 | F16: 350 | G16: 200
A17: R_115 | B17: Standard | C17: Twin Vista | D17: 2 | E17: 450 | F17: 350 | G17: 200
A18: R_116 | B18: Standard | C18: Budget Balcony | D18: 2 | E18: 450 | F18: 350 | G18: 200
A19: R_117 | B19: Deluxe | C19: Sunset Suite | D19: 3 | E19: 700 | F19: 600 | G19: 450
A20: R_118 | B20: Deluxe | C20: Lagoon View | D20: 3 | E20: 700 | F20: 600 | G20: 400
A21: R_119 | B21: Deluxe | C21: Heritage Room | D21: 3 | E21: 700 | F21: 600 | G21: 400
A22: R_120 | B22: Executive | C22: Diamond Villa | D22: 6 | E22: 1800 | F22: 1700 | G22: 1400

Sheet Booking_Data
A1: Guest Name | B1: Season | C1: Room_Type | D1: Adults | E1: Children | F1: Total_Guests | G1: Nights | H1: Price_Per_Night | I1: Spa_Service | J1: Room_Service | K1: Late_ Check-out | L1: Laundry_ Service | M1: Total_ Revenue | N1: Operating_Revenue | O1: Net_Profit | P1: Financial_Status
A2: John Miller | B2: Summer | C2: Grand Villa | D2: 4 | E2: 2 | F2: =SUM(D2,E2) -> 6 | G2: 3 | H2: =(IF(B2="Summer", VLOOKUP(TRIM(C2), Resort_Rates!$C$3:$P$13, 3, FALSE), VLOOKUP(TRIM(C2), Resort_Rates!$C$3:$P$13, 4, FALSE) ) )*F2 -> 10800 | I2: 250 | J2: 50 | K2: 100 | L2: 30 | M2: =(H2*G2)+SUM(I2:L2) -> 32830 | N2: =((VLOOKUP(C2,Resort_Rates!$C$3:$G$24,5,FALSE)*G2)*F2)+SUM(I2:L2) -> 21130 | O2: =M2-N2 -> 11700 | P2: =IF(O2<0,"Loss","Profit") -> Profit
A3: Sarah Reed | B3: Summer | C3: Solo Cabana | D3: 1 | E3: 0 | F3: =SUM(D3,E3) -> 1 | G3: 2 | H3: =(IF(B3="Summer", VLOOKUP(TRIM(C3), Resort_Rates!$C$3:$P$13, 3, FALSE), VLOOKUP(TRIM(C3), Resort_Rates!$C$3:$P$13, 4, FALSE) ) )*F3 -> 300 | I3: 0 | J3: 50 | K3: 0 | L3: 30 | M3: =(H3*G3)+SUM(I3:L3) -> 680 | N3: =((VLOOKUP(C3,Resort_Rates!$C$3:$G$24,5,FALSE)*G3)*F3)+SUM(I3:L3) -> 600 | O3: =M3-N3 -> 80 | P3: =IF(O3<0,"Loss","Profit") -> Profit
A4: Keisha Cole | B4: Winter | C4: Presidential | D4: 2 | E4: 2 | F4: =SUM(D4,E4) -> 4 | G4: 5 | H4: =(IF(B4="Summer", VLOOKUP(TRIM(C4), Resort_Rates!$C$3:$P$13, 3, FALSE), VLOOKUP(TRIM(C4), Resort_Rates!$C$3:$P$13, 4, FALSE) ) )*F4 -> 4400 | I4: 250 | J4: 50 | K4: 0 | L4: 30 | M4: =(H4*G4)+SUM(I4:L4) -> 22330 | N4: =((VLOOKUP(C4,Resort_Rates!$C$3:$G$24,5,FALSE)*G4)*F4)+SUM(I4:L4) -> 16330 | O4: =M4-N4 -> 6000 | P4: =IF(O4<0,"Loss","Profit") -> Profit
A5: David Beck | B5: Winter | C5: Double Studio | D5: 2 | E5: 0 | F5: =SUM(D5,E5) -> 2 | G5: 4 | H5: =(IF(B5="Summer", VLOOKUP(TRIM(C5), Resort_Rates!$C$3:$P$13, 3, FALSE), VLOOKUP(TRIM(C5), Resort_Rates!$C$3:$P$13, 4, FALSE) ) )*F5 -> 700 | I5: 0 | J5: 50 | K5: 100 | L5: 30 | M5: =(H5*G5)+SUM(I5:L5) -> 2980 | N5: =((VLOOKUP(C5,Resort_Rates!$C$3:$G$24,5,FALSE)*G5)*F5)+SUM(I5:L5) -> 3140 | O5: =M5-N5 -> -160 | P5: =IF(O5<0,"Loss","Profit") -> Loss
A6: Robert Fox | B6: Summer | C6: Ocean View | D6: 2 | E6: 1 | F6: =SUM(D6,E6) -> 3 | G6: 7 | H6: =(IF(B6="Summer", VLOOKUP(TRIM(C6), Resort_Rates!$C$3:$P$13, 3, FALSE), VLOOKUP(TRIM(C6), Resort_Rates!$C$3:$P$13, 4, FALSE) ) )*F6 -> 2100 | I6: 250 | J6: 50 | K6: 100 | L6: 30 | M6: =(H6*G6)+SUM(I6:L6) -> 15130 | N6: =((VLOOKUP(C6,Resort_Rates!$C$3:$G$24,5,FALSE)*G6)*F6)+SUM(I6:L6) -> 13030 | O6: =M6-N6 -> 2100 | P6: =IF(O6<0,"Loss","Profit") -> Profit
A7: Emma Stone | B7: Summer | C7: Poolside Retreat | D7: 2 | E7: 0 | F7: =SUM(D7,E7) -> 2 | G7: 3 | H7: =(IF(B7="Summer", VLOOKUP(TRIM(C7), Resort_Rates!$C$3:$P$13, 3, FALSE), VLOOKUP(TRIM(C7), Resort_Rates!$C$3:$P$13, 4, FALSE) ) )*F7 -> 1100 | I7: 250 | J7: 50 | K7: 100 | L7: 30 | M7: =(H7*G7)+SUM(I7:L7) -> 3730 | N7: =((VLOOKUP(C7,Resort_Rates!$C$3:$G$24,5,FALSE)*G7)*F7)+SUM(I7:L7) -> 3130 | O7: =M7-N7 -> 600 | P7: =IF(O7<0,"Loss","Profit") -> Profit
A8: Tom Hanks | B8: Winter | C8: Junior Suite | D8: 2 | E8: 0 | F8: =SUM(D8,E8) -> 2 | G8: 2 | H8: =(IF(B8="Summer", VLOOKUP(TRIM(C8), Resort_Rates!$C$3:$P$13, 3, FALSE), VLOOKUP(TRIM(C8), Resort_Rates!$C$3:$P$13, 4, FALSE) ) )*F8 -> 1500 | I8: 250 | J8: 50 | K8: 0 | L8: 30 | M8: =(H8*G8)+SUM(I8:L8) -> 3330 | N8: =((VLOOKUP(C8,Resort_Rates!$C$3:$G$24,5,FALSE)*G8)*F8)+SUM(I8:L8) -> 3090 | O8: =M8-N8 -> 240 | P8: =IF(O8<0,"Loss","Profit") -> Profit
A9: Linda Yang | B9: Winter | C9: Twin Balcony | D9: 2 | E9: 0 | F9: =SUM(D9,E9) -> 2 | G9: 6 | H9: =(IF(B9="Summer", VLOOKUP(TRIM(C9), Resort_Rates!$C$3:$P$13, 3, FALSE), VLOOKUP(TRIM(C9), Resort_Rates!$C$3:$P$13, 4, FALSE) ) )*F9 -> 700 | I9: 0 | J9: 50 | K9: 0 | L9: 30 | M9: =(H9*G9)+SUM(I9:L9) -> 4280 | N9: =((VLOOKUP(C9,Resort_Rates!$C$3:$G$24,5,FALSE)*G9)*F9)+SUM(I9:L9) -> 4880 | O9: =M9-N9 -> -600 | P9: =IF(O9<0,"Loss","Profit") -> Loss
A10: Chris Pratt | B10: Summer | C10: Presidential | D10: 2 | E10: 2 | F10: =SUM(D10,E10) -> 4 | G10: 4 | H10: =(IF(B10="Summer", VLOOKUP(TRIM(C10), Resort_Rates!$C$3:$P$13, 3, FALSE), VLOOKUP(TRIM(C10), Resort_Rates!$C$3:$P$13, 4, FALSE) ) )*F10 -> 4800 | I10: 0 | J10: 50 | K10: 0 | L10: 30 | M10: =(H10*G10)+SUM(I10:L10) -> 19280 | N10: =((VLOOKUP(C10,Resort_Rates!$C$3:$G$24,5,FALSE)*G10)*F10)+SUM(I10:L10) -> 12880 | O10: =M10-N10 -> 6400 | P10: =IF(O10<0,"Loss","Profit") -> Profit
A11: Bella Hadid | B11: Winter | C11: Garden View | D11: 2 | E11: 0 | F11: =SUM(D11,E11) -> 2 | G11: 3 | H11: =(IF(B11="Summer", VLOOKUP(TRIM(C11), Resort_Rates!$C$3:$P$13, 3, FALSE), VLOOKUP(TRIM(C11), Resort_Rates!$C$3:$P$13, 4, FALSE) ) )*F11 -> 900 | I11: 250 | J11: 50 | K11: 0 | L11: 30 | M11: =(H11*G11)+SUM(I11:L11) -> 3030 | N11: =((VLOOKUP(C11,Resort_Rates!$C$3:$G$24,5,FALSE)*G11)*F11)+SUM(I11:L11) -> 3030 | O11: =M11-N11 -> 0 | P11: =IF(O11<0,"Loss","Profit") -> Profit

Sheet Analytic_Report
A1: Guests & Stay Summary | D1: Financial Performane Summary
A2: Total_Bookings | B2: =COUNTA(Booking_Data!A2:A11) -> 10 | D2: Summer_Total_Revenue | E2: =SUMIF(Booking_Data!B:B,"Summer",Booking_Data!M:M) -> 71650
A3: Total_Adults_Hosted | B3: =SUM(Booking_Data!D:D) -> 21 | D3: Winter_Total_Revenue | E3: =SUMIF(Booking_Data!B:B,"Winter",Booking_Data!M:M) -> 35950
A4: Total_Children_Hosted | B4: =SUM(Booking_Data!E:E) -> 7 | D4: Net_Gross_Revenue | E4: =SUM(E2,E3) -> 107600
A5: Total_Guests_Hosted | B5: =SUM(B3,B4) -> 28 | D5: Net_Operating_Revenue | E5: =SUM(Booking_Data!N:N) -> 81240
A6: Average_Nights_Per_Stayed | B6: =AVERAGE(Booking_Data!G:G) -> 3.9 | D6: Net_Annual_Profit | E6: =E4-E5 -> 26360
A7: Highest_Booking_Room | B7: =INDEX(Booking_Data!C2:C11, MATCH(MAX(Booking_Data!M2:M11), Booking_Data!M2:M11, 0)) -> Grand Villa | D7: Bussiness_Health | E7: =IF(E6>0,"Profit","Loss") -> Profit
B9: Charts
